{"datetime": [1583924221, 1584269821], "number_of_submissions": 16, "upvotes": [449, 326, 255, 133, 74, 60, 33, 11, 9, 8, 6, 5, 4, 0, 0, 0], "ud_ratio": [1.0, 0.98, 0.98, 0.97, 0.89, 0.81, 0.88, 0.69, 0.92, 0.72, 0.79, 0.77, 0.86, 0.4, 0.2, 0.31], "comments": [62, 48, 77, 24, 25, 10, 15, 30, 3, 13, 23, 2, 4, 4, 5, 15], "u_top10_comments": [[12, 187, 74, 49, 28, 48, 11, 10, 3, 2, 11], [6, 30, 155, 18, 9, -14, -58], [16, 108, 46, 33, 123, 11, 3, 12, 2, 2, 2], [5, 30, 48, 7, 13, 1], [8, 51, 35, 8, 11, 8, 5, 4, -17], [4, 23, 7, 2, -15], [7, 26, 11, 15, 6, 6, 2, 1], [16, 8, 13, 7, 2, 1, 2, 2, 3, 1, 1], [1, 2], [8, 7, 6, 3, 2, 1, 1, 1, -5], [16, 4, 5, 4, 3, 3, 4, 5, 5, 2, 0], [1, 2], [4, 5, 3, 2, 2], [2, 4, 2], [4, 3, 5, 1, 1], [6, 7, 2, 2, 1, 1, 1]], "awards": [[0, 0, 0, 0, 0, 0, 0, 0, 0, 0, 0, 0, 0, 0, 0, 0], [0, 0, 0, 0, 0, 0, 0, 0, 0, 0, 0, 0, 0, 0, 0, 0], [0, 0, 0, 0, 0, 0, 0, 0, 0, 0, 0, 0, 0, 0, 0, 0]], "uc_ratio": [7, 7, 3, 6, 3, 6, 2, 0, 3, 1, 0, 2, 1, null, null, null], "title_length": [[18, 16, 16, 6, 6, 6, 9, 7, 11, 3, 3, 2, 9, 3, 3, 2], [103, 94, 98, 39, 41, 32, 47, 37, 66, 14, 18, 21, 57, 22, 26, 11]], "time": [1584257178, 1584252620, 1584243092, 1584213457, 1584232833, 1584211677, 1584212176, 1584210600, 1584250973, 1584220474, 1584236860, 1584243607, 1584243664, 1584219427, 1584231092, 1584217634], "username": ["down-vote-mcgee", "major_wood_num2", "singleguy79", "CEOnnor", "HPScots", "end_traveler", "J_Keezey", "BrutonRd", "txdahlia", "cureforhiccupsat4am", "GSolrac", "blindedxfate", "youdontknowmeze", "rts__", "Indianfratguy", "Diamondshock"], "oc": [false, false, false, false, false, false, false, false, false, false, false, false, false, false, false, false]}