{"datetime": [1583300508, 1583646108], "number_of_submissions": 4, "upvotes": [5643, 0, 1, 0], "ud_ratio": [0.96, 0.44, 0.6, 0.17], "comments": [247, 0, 0, 6], "u_top10_comments": [[86, 331, 999, 157, 61, 40, 9, 7, 6, 14, 5], [0, 0], [0, 0], [2, 57, 3]], "awards": [[0, 0, 0, 0], [0, 0, 0, 0], [0, 0, 0, 0]], "uc_ratio": [23, null, null, 0], "title_length": [[9, 3, 6, 9], [71, 17, 42, 59]], "time": [1583602468, 1583651141, 1583651849, 1583613682], "username": ["MicroSofty88", "thetechballoon", "Basic2424", "wewewawa"], "oc": [false, false, false, false]}