{"datetime": [1583580128, 1583925728], "number_of_submissions": 32, "upvotes": [11, 4, 3, 2, 2, 2, 2, 2, 3, 2, 1, 1, 1, 1, 1, 1, 1, 1, 1, 1, 1, 1, 1, 0, 0, 0, 0, 0, 0, 0, 0, 0], "ud_ratio": [0.81, 0.73, 0.67, 0.57, 0.62, 0.67, 0.75, 0.75, 0.67, 0.75, 0.67, 0.67, 0.66, 0.6, 0.6, 0.66, 0.6, 0.66, 0.66, 0.67, 0.66, 0.66, 0.99, 0.5, 0.5, 0.5, 0.4, 0.4, 0.33, 0.4, 0.25, 0.25], "comments": [7, 0, 0, 8, 1, 0, 3, 1, 2, 8, 1, 0, 2, 10, 0, 9, 3, 3, 4, 0, 12, 3, 2, 1, 0, 2, 1, 2, 1, 0, 5, 1], "u_top10_comments": [[1, 3], [0, 0], [0, 0], [5, 5, 1, 3, 1, 1], [1, 6], [0, 0], [1, 1], [1, 1], [2, 2, 1], [4, 7, 3, 1, 0], [1, 1], [0, 0], [1, 1], [3, 19, 4, 2], [0, 0], [4, 3, 2, 1, 1], [3, 3, 1, 1], [2, 1, 1], [3, 0, 0, -1], [0, 0], [1, -1], [3, 2, 1, 1], [1, 2], [1, 1], [0, 0], [2, 1, 0], [1, 1], [2, 2, 1], [1, 3], [0, 0], [1, 1], [1, 2]], "awards": [[0, 0, 0, 0, 0, 0, 0, 0, 0, 0, 0, 0, 0, 0, 0, 0, 0, 0, 0, 0, 0, 0, 0, 0, 0, 0, 0, 0, 0, 0, 0, 0], [0, 0, 0, 0, 0, 0, 0, 0, 0, 0, 0, 0, 0, 0, 0, 0, 0, 0, 0, 0, 0, 0, 0, 0, 0, 0, 0, 0, 0, 0, 0, 0], [0, 0, 0, 0, 0, 0, 0, 0, 0, 0, 0, 0, 0, 0, 0, 0, 0, 0, 0, 0, 0, 0, 0, 0, 0, 0, 0, 0, 0, 0, 0, 0]], "uc_ratio": [2, null, null, 0, 2, null, 1, 2, 2, 0, 1, null, 0, 0, null, 0, 0, 0, 0, null, 0, 0, 0, null, null, null, null, null, null, null, null, null], "title_length": [[4, 10, 34, 13, 25, 43, 10, 8, 13, 11, 2, 10, 20, 14, 14, 7, 2, 4, 4, 7, 7, 5, 1, 9, 12, 19, 18, 9, 51, 12, 8, 7], [26, 60, 232, 87, 151, 245, 70, 38, 72, 57, 14, 88, 109, 78, 73, 41, 16, 20, 35, 35, 39, 35, 14, 51, 76, 111, 94, 39, 293, 89, 40, 30]], "time": [1583899701, 1583898587, 1583906932, 1583938886, 1583884944, 1583935335, 1583883198, 1583882075, 1583870276, 1583868064, 1583931989, 1583916193, 1583897909, 1583897766, 1583895822, 1583888438, 1583882173, 1583875915, 1583874851, 1583873421, 1583870196, 1583869574, 1583867124, 1583919929, 1583878085, 1583870899, 1583938105, 1583927304, 1583923556, 1583869262, 1583928112, 1583914779], "username": ["Ch1ckP3a5", "Gladari", "van_datascience", "surgical-spirit", "vegar7", "louisamarisa", "Sudden_Artist", "JealousPickle", "chromoscience", "eb36420", "evilqueen1234", "ahmadk001", "YOURMOM37", "get180d", "Kiwiboer1559", "Clinician", "StvLilly", "robespierrem", "awesomeblossoming", "johnterry870", "Zheer1", "Arteemiis", "makeupZlover", "Bookscrounger", "disobedientcats", "Ykk7", "PadreMaronn", "shadowslash", "HollyBly1", "CultistHeadpiece", "RadScott", "yankymonkey"], "oc": [false, false, false, false, false, false, false, false, false, false, false, false, false, false, false, false, false, false, false, false, false, false, false, false, false, false, false, false, false, false, false, false]}