{"datetime": [1584107017, 1584452617], "number_of_submissions": 6, "upvotes": [1189, 694, 429, 241, 105, 5], "ud_ratio": [0.95, 0.98, 0.95, 0.97, 0.96, 0.75], "comments": [83, 17, 30, 15, 3, 3], "u_top10_comments": [[23, 77, 11, 5, 8, 4, 3, 3, 8, 2, 2], [6, 40, 6, 4, 17, 2, 1], [8, 43, 53, 4, 12, 4, 4, 2, 1], [10, 7, 4, 2, 1, 1, 1, 1, 1, -1, 0], [2, 1, 1], [2, 2, 1]], "awards": [[0, 0, 0, 0, 0, 0], [0, 0, 0, 0, 0, 0], [0, 0, 0, 0, 0, 0]], "uc_ratio": [14, 41, 14, 16, 35, 2], "title_length": [[25, 16, 8, 11, 5, 3], [141, 81, 46, 61, 33, 17]], "time": [1584404656, 1584454153, 1584454855, 1584412515, 1584397769, 1584456591], "username": ["originalmetalqueen", "MysteryBay22", "One_Giant_Nostril", "opoponits", "mkultrasauce", "n_ephys"], "oc": [false, false, false, false, false, false]}