{"datetime": [1583502403, 1583848003], "number_of_submissions": 35, "upvotes": [8028, 2207, 530, 372, 344, 366, 260, 234, 185, 169, 127, 124, 98, 96, 94, 87, 78, 80, 73, 70, 68, 73, 63, 58, 58, 57, 50, 56, 39, 36, 28, 17, 13, 5, 5], "ud_ratio": [0.97, 0.98, 0.98, 0.98, 0.96, 0.95, 0.99, 0.97, 0.98, 0.95, 0.96, 0.96, 0.93, 0.97, 0.98, 0.98, 0.93, 0.97, 0.93, 0.94, 0.94, 0.9, 0.96, 0.92, 0.92, 0.93, 0.92, 0.92, 0.86, 0.92, 0.87, 0.86, 0.71, 0.58, 0.72], "comments": [105, 50, 4, 11, 13, 4, 3, 3, 8, 4, 5, 2, 4, 2, 5, 0, 1, 1, 2, 2, 2, 5, 2, 1, 1, 1, 2, 2, 3, 0, 0, 2, 1, 1, 0], "u_top10_comments": [[53, 419, 130, 147, 289, 34, 21, 22, 96, 8, 6], [25, 131, 50, 39, 15, 15, 11, 5, 6, 3, 3], [2, 4, 3], [5, 2, 2, 1, 1, 1], [4, 4, 3, 2, 3], [3, 1, 1, 1], [1, 1], [0, 0], [4, 2, 1, 1, 1], [2, 2, 1], [1, 5], [1, 2], [2, 7, 0], [2, 1, 1], [2, 2, 2], [0, 0], [0, 0], [0, 0], [1, 1], [1, 2], [1, 3], [2, 1, 1], [1, 2], [1, 1], [1, 1], [1, 2], [0, 0], [2, 2, 1], [2, 1, 0], [0, 0], [0, 0], [1, 2], [1, 2], [0, 0], [0, 0]], "awards": [[0, 0, 0, 0, 0, 0, 0, 0, 0, 0, 0, 0, 0, 0, 0, 0, 0, 0, 0, 0, 0, 0, 0, 0, 0, 0, 0, 0, 0, 0, 0, 0, 0, 0, 0], [0, 0, 0, 0, 0, 0, 0, 0, 0, 0, 0, 0, 0, 0, 0, 0, 0, 0, 0, 0, 0, 0, 0, 0, 0, 0, 0, 0, 0, 0, 0, 0, 0, 0, 0], [0, 0, 0, 0, 0, 0, 0, 0, 0, 0, 0, 0, 0, 0, 0, 0, 0, 0, 0, 0, 0, 0, 0, 0, 0, 0, 0, 0, 0, 0, 0, 0, 0, 0, 0]], "uc_ratio": [76, 44, 132, 34, 26, 92, 87, 78, 23, 42, 25, 62, 24, 48, 19, null, 78, 80, 36, 35, 34, 15, 32, 58, 58, 57, 25, 28, 13, null, null, 8, 13, 5, null], "title_length": [[9, 1, 2, 7, 5, 5, 6, 3, 5, 8, 3, 6, 2, 7, 7, 1, 7, 4, 2, 4, 2, 6, 5, 4, 3, 8, 5, 5, 1, 4, 4, 2, 2, 9, 4], [44, 5, 14, 36, 24, 31, 28, 17, 29, 43, 19, 24, 11, 43, 44, 7, 34, 15, 11, 17, 14, 33, 29, 22, 17, 43, 24, 28, 7, 27, 24, 12, 9, 52, 23]], "time": [1583790017, 1583843012, 1583792257, 1583848396, 1583796466, 1583853142, 1583842752, 1583855804, 1583858696, 1583850073, 1583822233, 1583814611, 1583808599, 1583810530, 1583795259, 1583824939, 1583823298, 1583799012, 1583847465, 1583827335, 1583826061, 1583848766, 1583809152, 1583835374, 1583827235, 1583795686, 1583847583, 1583814079, 1583841210, 1583824613, 1583821797, 1583790318, 1583857818, 1583854694, 1583860563], "username": ["FuckForeverEver", "Bradlee", "NOTETOSELFLESS3", "Sadistic_Love", "simbabloom", "FelixLaPoubelle", "MiPink_Milk", "Creatositive", "zinzinjo2", "zinzinjo2", "-KamiKaze", "-KamiKaze", "-KamiKaze", "DaddyLonglegsL", "phootphetish", "-KamiKaze", "-KamiKaze", "Handjob-z", "jimstarr82", "LettyBlack", "-KamiKaze", "zinzinjo2", "-KamiKaze", "Handjob-z", "-KamiKaze", "phootphetish", "jimstarr82", "lickmydik", "iamlesley", "-KamiKaze", "Handjob-z", "MaschMana", "FelixLaPoubelle", "FreckledPegger58", "GittinGud94"], "oc": [false, false, false, false, false, false, false, false, false, false, false, false, false, false, false, false, false, false, false, false, false, false, false, false, false, false, false, false, false, false, false, false, false, false, false]}