{"datetime": [1583501492, 1583847092], "number_of_submissions": 46, "upvotes": [16269, 817, 717, 425, 410, 295, 221, 200, 133, 113, 117, 98, 106, 89, 74, 48, 42, 25, 16, 11, 11, 5, 5, 1, 0, 1, 0, 0, 0, 0, 0, 0, 0, 0, 0, 0, 0, 0, 0, 0, 0, 0, 0, 0, 0, 0], "ud_ratio": [0.92, 0.92, 0.96, 0.95, 0.9, 0.9, 0.91, 0.94, 0.84, 0.89, 0.98, 0.86, 0.91, 0.8, 0.79, 0.63, 0.82, 0.72, 0.74, 0.69, 0.61, 0.64, 0.56, 0.51, 0.58, 0.54, 0.48, 0.5, 0.44, 0.5, 0.54, 0.46, 0.38, 0.3, 0.47, 0.25, 0.38, 0.33, 0.33, 0.29, 0.43, 0.31, 0.24, 0.34, 0.16, 0.25], "comments": [480, 240, 231, 28, 112, 55, 49, 40, 13, 45, 41, 45, 28, 89, 71, 69, 3, 7, 271, 4, 5, 12, 5, 62, 9, 33, 2, 62, 7, 17, 23, 15, 1, 3, 7, 6, 3, 11, 22, 11, 30, 4, 12, 13, 8, 14], "u_top10_comments": [[181, 1830, 298, 139, 510, 84, 22, 47, 24, 33, 52], [34, 253, 137, 198, 77, 18, 25, 28, 63, 6, 53], [47, 1, 192, 65, 28, 200, 48, 13, 69, 10, 10], [16, 29, 67, 13, 3, 5, 2, 2, 1, 1, 1], [28, 233, 65, 27, 6, 4, 8, 4, 3, 3, 3], [20, 230, 43, 32, 9, 8, 11, 5, 5, 2, 6], [12, 86, 25, 6, 10, 7, 1, 8, 3, 1, 1], [12, 112, 24, 8, 5, 3, 2, 1, 1, 0, 1], [8, 41, 22, 3, 2, 2, 2, 1, 1], [10, 69, 15, 9, 33, 4, 15, 1, 1, 1, 1], [17, 39, 15, 10, 8, 5, 7, 3, 2, 3, 3], [13, 14, 3, 2, 4, 2, 1, 1, 1, 1, 1], [8, 40, 28, 9, 6, 4, 1, 1, -23], [15, 56, 12, 11, 9, 20, 11, 3, 2, 7, 1], [24, 119, 36, 51, 19, 20, 17, 9, 6, 4, 3], [38, 58, 14, 18, 6, 12, 9, 6, 3, 2, 2], [3, 5, 1, 1], [3, 5, 2, 1], [62, 5, 3, 4, 5, 3, 3, 3, 2, 2, 2], [2, 3, 2], [4, 12, 1, 1, -7], [5, 6, 2, 1, 1, 1], [1, 10], [40, 38, 6, 6, 14, 4, 10, 3, 3, 3, 3], [8, 4, 2, 3, 1, 1, 1, 1, -1], [13, 21, 8, 7, 8, 3, 3, 2, 2, 1, 1], [1, 1], [30, 9, 16, 5, 3, 3, 2, 2, 2, 2, 2], [3, 6, 3, 2], [14, 6, 5, 5, 2, 2, 2, 2, 2, 2, 1], [11, 9, 7, 14, 5, 2, 2, 4, 1, 1, 1], [9, 10, 5, 2, 1, 1, 1, 1, 1, 1], [1, 13], [3, 3, 1, 1], [7, 11, 7, 6, 4, 2, 1, 0], [3, 1, 1, 0], [2, 3, 2], [6, 6, 3, 1, 1, 1, 1], [16, 8, 9, 6, 7, 4, 6, 2, 2, 2, 2], [4, 12, 3, 1, 1], [18, 7, 3, 3, 5, 2, 3, 2, 1, 1, 1], [3, 8, 2, 2], [4, 10, 6, 6, 4], [8, 5, 13, 4, 2, 2, 1, -2, 0], [6, 8, 2, 1, 1, 0, 0], [4, 12, 2, 1, 1]], "awards": [[1, 0, 0, 0, 0, 0, 0, 0, 0, 0, 0, 0, 0, 0, 0, 0, 0, 0, 0, 0, 0, 0, 0, 0, 0, 0, 0, 0, 0, 0, 0, 0, 0, 0, 0, 0, 0, 0, 0, 0, 0, 0, 0, 0, 0, 0], [0, 0, 0, 0, 0, 0, 0, 0, 0, 0, 0, 0, 0, 0, 0, 0, 0, 0, 0, 0, 0, 0, 0, 0, 0, 0, 0, 0, 0, 0, 0, 0, 0, 0, 0, 0, 0, 0, 0, 0, 0, 0, 0, 0, 0, 0], [0, 0, 0, 0, 0, 0, 0, 0, 0, 0, 0, 0, 0, 0, 0, 0, 0, 0, 0, 0, 0, 0, 0, 0, 0, 0, 0, 0, 0, 0, 0, 0, 0, 0, 0, 0, 0, 0, 0, 0, 0, 0, 0, 0, 0, 0]], "uc_ratio": [34, 3, 3, 15, 4, 5, 5, 5, 10, 3, 3, 2, 4, 1, 1, 1, 14, 4, 0, 3, 2, 0, 1, 0, null, 0, null, null, null, null, null, null, null, null, null, null, null, null, null, null, null, null, null, null, null, null], "title_length": [[9, 9, 12, 9, 15, 6, 13, 7, 8, 9, 12, 13, 11, 38, 9, 15, 14, 11, 5, 8, 17, 7, 15, 14, 8, 26, 9, 28, 8, 10, 11, 4, 13, 6, 6, 7, 9, 9, 5, 9, 7, 11, 6, 7, 11, 13], [37, 59, 86, 67, 84, 40, 78, 43, 58, 71, 83, 70, 71, 233, 54, 84, 75, 63, 54, 54, 89, 36, 72, 62, 44, 154, 46, 139, 40, 60, 74, 25, 62, 36, 28, 38, 53, 46, 31, 51, 35, 63, 30, 32, 75, 65]], "time": [1583835306, 1583840886, 1583848020, 1583816801, 1583790966, 1583821827, 1583820376, 1583851612, 1583799237, 1583845014, 1583858008, 1583845676, 1583856446, 1583850254, 1583839337, 1583799024, 1583860544, 1583807429, 1583838052, 1583860083, 1583841639, 1583859605, 1583806399, 1583849399, 1583823800, 1583790377, 1583849848, 1583842637, 1583810461, 1583810443, 1583808843, 1583805920, 1583806319, 1583789761, 1583788762, 1583835596, 1583804310, 1583788367, 1583840169, 1583817525, 1583795460, 1583804181, 1583815824, 1583790245, 1583800512, 1583848540], "username": ["Morimot", "Frocharocha", "Frocharocha", "i_AM_hank", "DonnyLurch", "yuxbni76", "Tropiux", "Amiibofan101", "awkwardreader", "Frocharocha", "XDitto", "raisinbizzle", "Amiibofan101", "bengalsfu", "shaokpro", "Draigh1981", "CaspianX2", "TheSillyPenguin", "AutoModerator", "EvoR", "flanneltuesday", "FourStringL0B0", "codeword_hwhisky", "macht27", "Kingjosiahd", "bluedestiny88", "BattleStadium", "apexandedibles", "Julian15Ortega", "Captain-fach", "TheBlueImpulse", "PichuAngel", "Crimsonclaw111", "Vesemix", "kevaddams", "Junees19999", "StreetsofRagequit", "scott_fly", "Alazana", "ohnoihaveabluechair", "Vainglorious_Reim", "wormoo", "sweglord69420", "furretguy", "lexsteve28", "TakeMeArachne"], "oc": [false, false, false, true, false, false, false, false, false, false, false, false, false, false, false, false, false, false, false, false, false, false, false, false, false, false, false, false, false, false, false, false, false, false, false, false, false, false, false, false, false, false, false, false, false, false]}