{"datetime": [1584181918, 1584527518], "number_of_submissions": 5, "upvotes": [3089, 21, 3, 4, 3], "ud_ratio": [0.97, 0.79, 0.6, 0.67, 0.67], "comments": [155, 3, 2, 4, 4], "u_top10_comments": [[30, 67, 239, 157, 44, 68, 11, 33, 26, 18, 11], [1, 2], [2, 1, 1], [2, 3, 2], [1, 4]], "awards": [[0, 0, 0, 0, 0], [0, 0, 0, 0, 0], [0, 0, 0, 0, 0]], "uc_ratio": [20, 7, 2, 1, 1], "title_length": [[18, 22, 31, 7, 6], [104, 157, 212, 45, 49]], "time": [1584497846, 1584491843, 1584541743, 1584495815, 1584465360], "username": ["ibn-aws", "danielkuhn", "chopin238", "RB5Network", "ADefiniteDescription"], "oc": [false, false, false, false, false]}